{
  "results" : [ {
    "graph_id" : 1,
    "input_stats" : {
      "vertices" : 5,
      "edges" : 4
    },
    "prim" : {
      "mst_edges" : [ {
        "from" : "A",
        "to" : "B",
        "weight" : 2.0
      }, {
        "from" : "B",
        "to" : "C",
        "weight" : 3.0
      }, {
        "from" : "C",
        "to" : "D",
        "weight" : 4.0
      }, {
        "from" : "D",
        "to" : "E",
        "weight" : 5.0
      } ],
      "total_cost" : 14.0,
      "operations_count" : 8,
      "execution_time_ms" : 0.0306,
      "error" : null
    },
    "kruskal" : {
      "mst_edges" : [ {
        "from" : "A",
        "to" : "B",
        "weight" : 2.0
      }, {
        "from" : "B",
        "to" : "C",
        "weight" : 3.0
      }, {
        "from" : "C",
        "to" : "D",
        "weight" : 4.0
      }, {
        "from" : "D",
        "to" : "E",
        "weight" : 5.0
      } ],
      "total_cost" : 14.0,
      "operations_count" : 29,
      "execution_time_ms" : 0.023,
      "error" : null
    }
  }, {
    "graph_id" : 2,
    "input_stats" : {
      "vertices" : 5,
      "edges" : 7
    },
    "prim" : {
      "mst_edges" : [ {
        "from" : "A",
        "to" : "B",
        "weight" : 3.0
      }, {
        "from" : "A",
        "to" : "C",
        "weight" : 3.0
      }, {
        "from" : "B",
        "to" : "D",
        "weight" : 4.0
      }, {
        "from" : "C",
        "to" : "E",
        "weight" : 5.0
      } ],
      "total_cost" : 15.0,
      "operations_count" : 24,
      "execution_time_ms" : 0.0165,
      "error" : null
    },
    "kruskal" : {
      "mst_edges" : [ {
        "from" : "A",
        "to" : "B",
        "weight" : 3.0
      }, {
        "from" : "A",
        "to" : "C",
        "weight" : 3.0
      }, {
        "from" : "B",
        "to" : "D",
        "weight" : 4.0
      }, {
        "from" : "C",
        "to" : "E",
        "weight" : 5.0
      } ],
      "total_cost" : 15.0,
      "operations_count" : 45,
      "execution_time_ms" : 0.0124,
      "error" : null
    }
  }, {
    "graph_id" : 3,
    "input_stats" : {
      "vertices" : 4,
      "edges" : 6
    },
    "prim" : {
      "mst_edges" : [ {
        "from" : "A",
        "to" : "B",
        "weight" : 2.0
      }, {
        "from" : "A",
        "to" : "C",
        "weight" : 3.0
      }, {
        "from" : "A",
        "to" : "D",
        "weight" : 4.0
      } ],
      "total_cost" : 9.0,
      "operations_count" : 19,
      "execution_time_ms" : 0.0113,
      "error" : null
    },
    "kruskal" : {
      "mst_edges" : [ {
        "from" : "A",
        "to" : "B",
        "weight" : 2.0
      }, {
        "from" : "A",
        "to" : "C",
        "weight" : 3.0
      }, {
        "from" : "A",
        "to" : "D",
        "weight" : 4.0
      } ],
      "total_cost" : 9.0,
      "operations_count" : 20,
      "execution_time_ms" : 0.007,
      "error" : null
    }
  }, {
    "graph_id" : 4,
    "input_stats" : {
      "vertices" : 6,
      "edges" : 13
    },
    "prim" : {
      "mst_edges" : [ {
        "from" : "A",
        "to" : "B",
        "weight" : 2.0
      }, {
        "from" : "F",
        "to" : "A",
        "weight" : 2.0
      }, {
        "from" : "B",
        "to" : "E",
        "weight" : 2.0
      }, {
        "from" : "A",
        "to" : "D",
        "weight" : 2.0
      }, {
        "from" : "C",
        "to" : "F",
        "weight" : 2.0
      } ],
      "total_cost" : 10.0,
      "operations_count" : 50,
      "execution_time_ms" : 0.0191,
      "error" : null
    },
    "kruskal" : {
      "mst_edges" : [ {
        "from" : "A",
        "to" : "B",
        "weight" : 2.0
      }, {
        "from" : "F",
        "to" : "A",
        "weight" : 2.0
      }, {
        "from" : "A",
        "to" : "D",
        "weight" : 2.0
      }, {
        "from" : "B",
        "to" : "E",
        "weight" : 2.0
      }, {
        "from" : "C",
        "to" : "F",
        "weight" : 2.0
      } ],
      "total_cost" : 10.0,
      "operations_count" : 60,
      "execution_time_ms" : 0.0157,
      "error" : null
    }
  }, {
    "graph_id" : 5,
    "input_stats" : {
      "vertices" : 6,
      "edges" : 3
    },
    "prim" : {
      "mst_edges" : [ ],
      "total_cost" : null,
      "operations_count" : 4,
      "execution_time_ms" : 0.0097,
      "error" : "Graph is disconnected (no MST)."
    },
    "kruskal" : {
      "mst_edges" : [ ],
      "total_cost" : null,
      "operations_count" : 21,
      "execution_time_ms" : 0.0095,
      "error" : "Graph is disconnected (no MST)."
    }
  }, {
    "graph_id" : 6,
    "input_stats" : {
      "vertices" : 5,
      "edges" : 7
    },
    "prim" : {
      "mst_edges" : [ {
        "from" : "A",
        "to" : "C",
        "weight" : 3.0
      }, {
        "from" : "B",
        "to" : "C",
        "weight" : 2.0
      }, {
        "from" : "B",
        "to" : "D",
        "weight" : 5.0
      }, {
        "from" : "D",
        "to" : "E",
        "weight" : 6.0
      } ],
      "total_cost" : 16.0,
      "operations_count" : 25,
      "execution_time_ms" : 0.0176,
      "error" : null
    },
    "kruskal" : {
      "mst_edges" : [ {
        "from" : "B",
        "to" : "C",
        "weight" : 2.0
      }, {
        "from" : "A",
        "to" : "C",
        "weight" : 3.0
      }, {
        "from" : "B",
        "to" : "D",
        "weight" : 5.0
      }, {
        "from" : "D",
        "to" : "E",
        "weight" : 6.0
      } ],
      "total_cost" : 16.0,
      "operations_count" : 39,
      "execution_time_ms" : 0.0148,
      "error" : null
    }
  } ]
}